{
    "results": [
      {
        "objectId": "szAeHIS5aw",
        "geonameid": 2561668,
        "name": "Agadir",
        "asciiname": "Agadir",
        "alternatenames": "AGA,Agadair,Agadir,Agadir - akadyr,Agadir - اكادير,Agadir Ighir,Agadiras,Agádír,Ankantir,Irhir,Santa Cruz,a jia di er,agadileu,agadira,agadiru,agadyr,aghadyr,akadyr,aݣadyr,Αγκαντίρ,Агадир,Агадір,אגאדיר,أغادير,أكادير,أگادیر,أݣادير,اغادیر,اگادیر,अगादिर,アガディール,阿加迪尔,아가디르",
        "latitude": 30.42018,
        "longitude": -9.59815,
        "feature_class": "P",
        "feature_code": "PPLA",
        "country_code": "MA",
        "admin1_code": 9,
        "admin2_code": 1,
        "admin3_code": 400101011,
        "population": 698310,
        "dem": 31,
        "timezone": "Africa/Casablanca",
        "modification_date": "2019-05-09",
        "createdAt": "2020-12-15T12:45:37.997Z",
        "updatedAt": "2020-12-15T12:45:37.997Z"
      },
      {
        "objectId": "5RSjuQ6ZhK",
        "geonameid": 2561124,
        "name": "Ahfir",
        "asciiname": "Ahfir",
        "alternatenames": "Ahfir,Martimprey du Kiss",
        "latitude": 34.95368,
        "longitude": -2.10027,
        "feature_class": "P",
        "feature_code": "PPLA3",
        "country_code": "MA",
        "admin1_code": 2,
        "admin2_code": 113,
        "admin3_code": 811301011,
        "population": 19611,
        "dem": 252,
        "timezone": "Africa/Casablanca",
        "modification_date": "2016-11-02",
        "createdAt": "2020-12-15T12:45:37.997Z",
        "updatedAt": "2020-12-15T12:45:37.997Z"
      },
      {
        "objectId": "Ib0ObgA3xx",
        "geonameid": 2560922,
        "name": "Aïn Beni Mathar",
        "asciiname": "Ain Beni Mathar",
        "alternatenames": "Ain Beni Mathar,Ajn Bni Matar,Aïn Beni Mathar,Beni Mattar Ahel Ras-el-Ain,Berguent,Ras el Ain des Beni Mathar,Ras el Aïn des Beni Mathar,Айн Бни Матар",
        "latitude": 34.0097,
        "longitude": -2.03238,
        "feature_class": "P",
        "feature_code": "PPL",
        "country_code": "MA",
        "admin1_code": 2,
        "admin2_code": 275,
        "population": 16289,
        "dem": 917,
        "timezone": "Africa/Casablanca",
        "modification_date": "2018-08-15",
        "createdAt": "2020-12-15T12:45:37.997Z",
        "updatedAt": "2020-12-15T12:45:37.997Z"
      },
      {
        "objectId": "ixnIvFeffv",
        "geonameid": 2560813,
        "name": "Aïn Leuh",
        "asciiname": "Ain Leuh",
        "alternatenames": "Ain Leuh,Ajn Ljokh,Aïn Leuh,Айн Лёх",
        "latitude": 33.28984,
        "longitude": -5.33863,
        "feature_class": "P",
        "feature_code": "PPL",
        "country_code": "MA",
        "admin1_code": 3,
        "population": 5278,
        "dem": 1424,
        "timezone": "Africa/Casablanca",
        "modification_date": "2018-08-06",
        "createdAt": "2020-12-15T12:45:37.997Z",
        "updatedAt": "2020-12-15T12:45:37.997Z"
      },
      {
        "objectId": "NY0GP5GjP2",
        "geonameid": 9645312,
        "name": "Akhfennir",
        "asciiname": "Akhfennir",
        "latitude": 28.09455,
        "longitude": -12.05157,
        "feature_class": "P",
        "feature_code": "PPL",
        "country_code": "MA",
        "admin1_code": 11,
        "admin2_code": 121,
        "population": 1583,
        "dem": 15,
        "timezone": "Africa/Casablanca",
        "modification_date": "2016-11-04",
        "createdAt": "2020-12-15T12:45:39.525Z",
        "updatedAt": "2020-12-15T12:45:39.525Z"
      },
      {
        "objectId": "pu6JL9PIU1",
        "geonameid": 2542013,
        "name": "Al Aaroui",
        "asciiname": "Al Aaroui",
        "alternatenames": "Al Aaroui,Mont Arrouit,Mont-Aroui,Mont-Arruit,Monte 'Arrouit,Monte Arruit,Monte ’Arrouit",
        "latitude": 35.0109,
        "longitude": -3.00938,
        "feature_class": "P",
        "feature_code": "PPL",
        "country_code": "MA",
        "admin1_code": 2,
        "population": 36021,
        "dem": 177,
        "timezone": "Africa/Casablanca",
        "modification_date": "2017-12-06",
        "createdAt": "2020-12-15T12:45:37.997Z",
        "updatedAt": "2020-12-15T12:45:37.997Z"
      },
      {
        "objectId": "CJnsbnCZsn",
        "geonameid": 2548830,
        "name": "Al Fqih Ben Çalah",
        "asciiname": "Al Fqih Ben Calah",
        "alternatenames": "Al Fqih Ben Calah,Al Fqih Ben Çalah,Fkih Ben Salah,Fquih Ben Salah",
        "latitude": 32.50213,
        "longitude": -6.68771,
        "feature_class": "P",
        "feature_code": "PPL",
        "country_code": "MA",
        "admin1_code": 5,
        "admin2_code": 255,
        "population": 84072,
        "dem": 444,
        "timezone": "Africa/Casablanca",
        "modification_date": "2020-06-11",
        "createdAt": "2020-12-15T12:45:37.997Z",
        "updatedAt": "2020-12-15T12:45:37.997Z"
      },
      {
        "objectId": "D0m349fTuw",
        "geonameid": 2558545,
        "name": "Al Hoceïma",
        "asciiname": "Al Hoceima",
        "alternatenames": "AHU,Al Hoceima,Al Hoceïma,Al Huceima,Al Husaymat,Al Ḩusaymāt,Al-Hoceima,Al-Husajma,Alhacemas,Alhucemas,Villa Alhucemas,Villa Sanjurjo,alhsymt,hsymh,الحسيمة,حسیمه",
        "latitude": 35.25165,
        "longitude": -3.93723,
        "feature_class": "P",
        "feature_code": "PPLA2",
        "country_code": "MA",
        "admin1_code": 1,
        "admin2_code": 51,
        "population": 395644,
        "dem": 74,
        "timezone": "Africa/Casablanca",
        "modification_date": "2016-11-03",
        "createdAt": "2020-12-15T12:45:37.997Z",
        "updatedAt": "2020-12-15T12:45:37.997Z"
      },
      {
        "objectId": "PGbnEbR6M2",
        "geonameid": 2549356,
        "name": "Arfoud",
        "asciiname": "Arfoud",
        "alternatenames": "Arfoud,Ehrfud,Erfoud,Эрфуд",
        "latitude": 31.4353,
        "longitude": -4.23258,
        "feature_class": "P",
        "feature_code": "PPL",
        "country_code": "MA",
        "admin1_code": 8,
        "admin2_code": 201,
        "population": 23637,
        "dem": 809,
        "timezone": "Africa/Casablanca",
        "modification_date": "2019-10-21",
        "createdAt": "2020-12-15T12:45:37.997Z",
        "updatedAt": "2020-12-15T12:45:37.997Z"
      },
      {
        "objectId": "49z4KpOBM9",
        "geonameid": 2557055,
        "name": "Asilah",
        "asciiname": "Asilah",
        "alternatenames": "Arcila,Arcilas,Arsila,Arzila,Arzilah,Arzīlah,Asila,Asilah,Asilakh,Assila,Assilah,Augusta Zilil,Aṣīla,Colonia Augusti Iulia Constantia Zilil,Ville d'Arcila,Ville d’Arcila,ashira,asilla,asylh,asylt,sylt,Асила,Асилах,أصيلة,اصیله,صيلة,アシラー,아실라",
        "latitude": 35.46522,
        "longitude": -6.03415,
        "feature_class": "P",
        "feature_code": "PPL",
        "country_code": "MA",
        "admin1_code": 1,
        "admin2_code": 511,
        "population": 28861,
        "dem": 17,
        "timezone": "Africa/Casablanca",
        "modification_date": "2016-11-04",
        "createdAt": "2020-12-15T12:45:37.997Z",
        "updatedAt": "2020-12-15T12:45:37.997Z"
      },
      {
        "objectId": "KgXtOkrwqx",
        "geonameid": 2556657,
        "name": "Azemmour",
        "asciiname": "Azemmour",
        "alternatenames": "Azamor,Azemmour,Azimur,Azzegour",
        "latitude": 33.28952,
        "longitude": -8.3425,
        "feature_class": "P",
        "feature_code": "PPLA3",
        "country_code": "MA",
        "admin1_code": 6,
        "admin2_code": 181,
        "admin3_code": 1118101011,
        "population": 37140,
        "dem": 28,
        "timezone": "Africa/Casablanca",
        "modification_date": "2016-11-02",
        "createdAt": "2020-12-15T12:45:37.997Z",
        "updatedAt": "2020-12-15T12:45:37.997Z"
      },
      {
        "objectId": "frE0DLMkGs",
        "geonameid": 2556464,
        "name": "Azrou",
        "asciiname": "Azrou",
        "alternatenames": "Azrou,Azru,Azrú,ai zi lu,azrw,Азру,أزرو,ازرو,艾茲魯",
        "latitude": 33.43443,
        "longitude": -5.22126,
        "feature_class": "P",
        "feature_code": "PPLA3",
        "country_code": "MA",
        "admin1_code": 3,
        "admin2_code": 271,
        "admin3_code": 1327101011,
        "population": 48249,
        "dem": 1277,
        "timezone": "Africa/Casablanca",
        "modification_date": "2016-11-02",
        "createdAt": "2020-12-15T12:45:37.997Z",
        "updatedAt": "2020-12-15T12:45:37.997Z"
      },
      {
        "objectId": "351Xoj3Wrp",
        "geonameid": 2555745,
        "name": "Beni Mellal",
        "asciiname": "Beni Mellal",
        "alternatenames": "Ayt Mellal,BEM,Bani Mallal,Beni Melal,Beni Melalis,Beni Mellal,Beni-Mellal,Beni-Mellal',Beni-Mellal-Centre,Béni Mellal,Béni-Mellal,bei ni mai la lei,benimellal,bny mlal,bny mll,Бени-Меллаль,בני מלל,بني ملال,بنی ملال,بنی‌ملال,貝尼邁拉勒,베니멜랄",
        "latitude": 32.33725,
        "longitude": -6.34983,
        "feature_class": "P",
        "feature_code": "PPLA",
        "country_code": "MA",
        "admin1_code": 5,
        "admin2_code": 91,
        "admin3_code": 1209109012,
        "population": 166399,
        "dem": 538,
        "timezone": "Africa/Casablanca",
        "modification_date": "2017-02-03",
        "createdAt": "2020-12-15T12:45:37.997Z",
        "updatedAt": "2020-12-15T12:45:37.997Z"
      },
      {
        "objectId": "yLK2kWgnla",
        "geonameid": 2555467,
        "name": "Berkane",
        "asciiname": "Berkane",
        "alternatenames": "Berkan,Berkane,Berkawe,Berkán,Birkani,bai er kan,brkan,Беркан,بركان,برکان,拜爾坎",
        "latitude": 34.92,
        "longitude": -2.32,
        "feature_class": "P",
        "feature_code": "PPLA3",
        "country_code": "MA",
        "admin1_code": 2,
        "admin2_code": 113,
        "admin3_code": 811301091,
        "population": 80721,
        "dem": 173,
        "timezone": "Africa/Casablanca",
        "modification_date": "2016-11-02",
        "createdAt": "2020-12-15T12:45:37.997Z",
        "updatedAt": "2020-12-15T12:45:37.997Z"
      },
      {
        "objectId": "oOYLi5AXA4",
        "geonameid": 2556272,
        "name": "Berrechid",
        "asciiname": "Berrechid",
        "alternatenames": "Barrechid,Berrechid,Bev-rechid",
        "latitude": 33.26553,
        "longitude": -7.58754,
        "feature_class": "P",
        "feature_code": "PPLA3",
        "country_code": "MA",
        "admin1_code": 6,
        "admin2_code": 461,
        "admin3_code": 646101031,
        "population": 93954,
        "dem": 220,
        "timezone": "Africa/Casablanca",
        "modification_date": "2016-11-02",
        "createdAt": "2020-12-15T12:45:37.997Z",
        "updatedAt": "2020-12-15T12:45:37.997Z"
      },
      {
        "objectId": "Br2ZjJpVEm",
        "geonameid": 10958491,
        "name": "Bni Bouayach",
        "asciiname": "Bni Bouayach",
        "alternatenames": "Bni Bojazh,Bni Bouayach,Бни Бояж",
        "latitude": 35.10506,
        "longitude": -3.84028,
        "feature_class": "P",
        "feature_code": "PPL",
        "country_code": "MA",
        "admin1_code": 1,
        "population": 18271,
        "dem": 118,
        "timezone": "Africa/Casablanca",
        "modification_date": "2018-06-10",
        "createdAt": "2020-12-15T12:45:39.525Z",
        "updatedAt": "2020-12-15T12:45:39.525Z"
      },
      {
        "objectId": "4Rz6CQaNzZ",
        "geonameid": 2555157,
        "name": "Bouarfa",
        "asciiname": "Bouarfa",
        "alternatenames": "Bordj de Bou Arfa,Bou Arfa,Bouafra,Buarfa,UAR",
        "latitude": 32.53379,
        "longitude": -1.96209,
        "feature_class": "P",
        "feature_code": "PPLA3",
        "country_code": "MA",
        "admin1_code": 2,
        "admin2_code": 251,
        "admin3_code": 825101011,
        "population": 28846,
        "dem": 1169,
        "timezone": "Africa/Casablanca",
        "modification_date": "2019-08-13",
        "createdAt": "2020-12-15T12:45:37.997Z",
        "updatedAt": "2020-12-15T12:45:37.997Z"
      },
      {
        "objectId": "0RIlHYqBpf",
        "geonameid": 6546693,
        "name": "Boujniba",
        "asciiname": "Boujniba",
        "alternatenames": "Boujniba,Boujniba (Commune Urbaine),Boujniba (MU),ابي الجعد (البلدية)",
        "latitude": 32.90046,
        "longitude": -6.77464,
        "feature_class": "P",
        "feature_code": "PPL",
        "country_code": "MA",
        "admin1_code": 5,
        "admin2_code": 311,
        "admin3_code": 631101031,
        "population": 15041,
        "dem": 847,
        "timezone": "Africa/Casablanca",
        "modification_date": "2016-11-02",
        "createdAt": "2020-12-15T12:45:39.525Z",
        "updatedAt": "2020-12-15T12:45:39.525Z"
      },
      {
        "objectId": "XyqTJoe3ei",
        "geonameid": 2553751,
        "name": "Bouznika",
        "asciiname": "Bouznika",
        "alternatenames": "Bouzhika,Bouznika,Bouzniqa,Buznike,Kasba bou Znika,Бузнике",
        "latitude": 33.78942,
        "longitude": -7.15968,
        "feature_class": "P",
        "feature_code": "PPLA3",
        "country_code": "MA",
        "admin1_code": 6,
        "admin2_code": 111,
        "admin3_code": 611101031,
        "population": 27283,
        "dem": 43,
        "timezone": "Africa/Casablanca",
        "modification_date": "2016-11-02",
        "createdAt": "2020-12-15T12:45:37.997Z",
        "updatedAt": "2020-12-15T12:45:37.997Z"
      },
      {
        "objectId": "sygeIAEGpk",
        "geonameid": 10955770,
        "name": "Cap Negro II",
        "asciiname": "Cap Negro II",
        "alternatenames": "Cabo Negro,Cap Negro II,Kabo Negro,Кабо Негро",
        "latitude": 35.6597,
        "longitude": -5.28525,
        "feature_class": "P",
        "feature_code": "PPL",
        "country_code": "MA",
        "admin1_code": 1,
        "population": 10000,
        "dem": 7,
        "timezone": "Africa/Casablanca",
        "modification_date": "2018-08-09",
        "createdAt": "2020-12-15T12:45:39.525Z",
        "updatedAt": "2020-12-15T12:45:39.525Z"
      },
      {
        "objectId": "1yzUEsjjB0",
        "geonameid": 2553604,
        "name": "Casablanca",
        "asciiname": "Casablanca",
        "alternatenames": "Ad Dar al Bayda,Ad Dar al Bayda',Ad Dār al Bayḑā’,Anafi,Anfa,CAS,Casa Branca,Casablanca,Casabranca,Dar-el-Beida,Dar-uel-Beyda,Darul Baidha,Dâr-ül-Beydâ,Ed Dar el Baida,Ed Dār el Baida,Kasablank,Kasablanka,Kasablankae,Kazablanka,Kazablanko,Kazamplan'ka,Tigemmi Tamellalt,White House,ad-Dar al-Baydaʼ,ad-Dar al-baydaʾ,ad-Dār al-Bayḍāʼ,ad-Dār al-bayḍāʾ,aldar albydaʾ,anfa,dar albydaʾ,daralbyda,ka sa bu lan ka,ka sab l xng ka,kacapilanka,kasabalanka,kasabeullangka,kasablanka,kasaburanka,kazablanka,qzblnqh,Καζαμπλάνκα,Казабланка,Касабланкæ,Касабланка,Կասաբլանկա,קזבלנקה,أنفا,الدار البيضاء,دار البیضاء,دارالبیضا,كازابلانكا,کازابلانکا,کاسابلانکا,कासाब्लांका,কাসাব্লাংকা,ਕਾਸਾਬਲਾਂਕਾ,காசாபிளாங்கா,కాసాబ్లాంకా,ಕಾಸಾಬ್ಲಾಂಕಾ,കാസബ്ലങ്ക,กาซาบล็องกา,ກາຊາບັງກາ,ကာဆာဘလန်ကာမြို့,კასაბლანკა,ⴰⵏⴼⴰ,カサブランカ,卡萨布兰卡,카사블랑카",
        "latitude": 33.58831,
        "longitude": -7.61138,
        "feature_class": "P",
        "feature_code": "PPLA",
        "country_code": "MA",
        "admin1_code": 6,
        "admin2_code": 141,
        "population": 3144909,
        "dem": 27,
        "timezone": "Africa/Casablanca",
        "modification_date": "2019-09-05",
        "createdAt": "2020-12-15T12:45:37.997Z",
        "updatedAt": "2020-12-15T12:45:37.997Z"
      },
      {
        "objectId": "IK0AQnvLH3",
        "geonameid": 2553455,
        "name": "Chefchaouene",
        "asciiname": "Chefchaouene",
        "alternatenames": "Chaouen,Chaouèn,Chauen,Chechaouen,Chechaouene,Chechaouèn,Chefchaouen,Chefchaouene,Chichaouene,Ech Chaouene,Scheschauen,Shefshauen,Ville de Chechaouen,Ville de Chechaouèn,Xauen,Xexauen,shfshawn,Шефшауен,شفشاون",
        "latitude": 35.16878,
        "longitude": -5.2636,
        "feature_class": "P",
        "feature_code": "PPLA2",
        "country_code": "MA",
        "admin1_code": 1,
        "admin2_code": 151,
        "population": 36280,
        "dem": 607,
        "timezone": "Africa/Casablanca",
        "modification_date": "2016-11-04",
        "createdAt": "2020-12-15T12:45:37.997Z",
        "updatedAt": "2020-12-15T12:45:37.997Z"
      },
      {
        "objectId": "zVP6bWxdi2",
        "geonameid": 8542188,
        "name": "Dakhla",
        "asciiname": "Dakhla",
        "alternatenames": "Dajla,Villa Cisneros,aldakhlt‎,الداخلة‎",
        "latitude": 30.41071,
        "longitude": -9.55572,
        "feature_class": "P",
        "feature_code": "PPLX",
        "country_code": "MA",
        "cc2": "EH",
        "population": 55618,
        "dem": 83,
        "timezone": "Africa/Casablanca",
        "modification_date": "2018-09-03",
        "createdAt": "2020-12-15T12:45:39.525Z",
        "updatedAt": "2020-12-15T12:45:39.525Z"
      },
      {
        "objectId": "2OWuujHuOL",
        "geonameid": 2550806,
        "name": "El Aïoun",
        "asciiname": "El Aioun",
        "alternatenames": "Aioun Sidi Mellouk,Al 'Youn,Al ’Youn,El Aioun,El Aioun Sidi Mellouk,El Aïoun,El Aïoun Sidi Mellouk",
        "latitude": 34.58319,
        "longitude": -2.50612,
        "feature_class": "P",
        "feature_code": "PPL",
        "country_code": "MA",
        "admin1_code": 2,
        "population": 35196,
        "dem": 604,
        "timezone": "Africa/Casablanca",
        "modification_date": "2020-06-11",
        "createdAt": "2020-12-15T12:45:37.997Z",
        "updatedAt": "2020-12-15T12:45:37.997Z"
      },
      {
        "objectId": "TZggxf59br",
        "geonameid": 2550252,
        "name": "El Hajeb",
        "asciiname": "El Hajeb",
        "latitude": 33.68786,
        "longitude": -5.371,
        "feature_class": "P",
        "feature_code": "PPLA3",
        "country_code": "MA",
        "admin1_code": 3,
        "admin2_code": 171,
        "admin3_code": 1317101051,
        "population": 28126,
        "dem": 1023,
        "timezone": "Africa/Casablanca",
        "modification_date": "2016-11-02",
        "createdAt": "2020-12-15T12:45:37.997Z",
        "updatedAt": "2020-12-15T12:45:37.997Z"
      },
      {
        "objectId": "SdqkALslHv",
        "geonameid": 2550078,
        "name": "El Jadid",
        "asciiname": "El Jadid",
        "alternatenames": "Al Jadida,Al Yadida,Al-Djadida,Al-Dzadida,Al-Dżadida,Al-Džadída,Castilho Real,Dzadida,Džadida,Ehl'-Dzhadida,Ehl'-Dzhadzida,El Jadid,El Jadida,El-Jadida,El-Yadida,Mazagan,Mazagao,Mazaghan,Mazagão,Mazargan,aljdydh,aljdydt,el-jadida,ela jadida,eljadida,jie di dai,xælcha di da,Мазарґан,Эль-Джадзіда,Эль-Джадида,אל-גדידה,الجديدة,الجدیده,الجدیدہ,एल जदिदा,แอลฌาดีดา,ელ-ჯადიდა,アル・ジャディーダ,杰迪代,엘자디다",
        "latitude": 33.25682,
        "longitude": -8.50882,
        "feature_class": "P",
        "feature_code": "PPL",
        "country_code": "MA",
        "admin1_code": 6,
        "admin2_code": 181,
        "population": 147549,
        "dem": 10,
        "timezone": "Africa/Casablanca",
        "modification_date": "2019-09-05",
        "createdAt": "2020-12-15T12:45:37.997Z",
        "updatedAt": "2020-12-15T12:45:37.997Z"
      },
      {
        "objectId": "Hbn0GOmNAt",
        "geonameid": 7280528,
        "name": "Errachidia",
        "asciiname": "Errachidia",
        "alternatenames": "Al-Rashidiyya,Ar-Raszidijja,ERH,Ehr-Rashidija,Er Rachidia,Er-Rachidia,Er-Rachidía,Errachidia,Imtɣeren,Ksar es-Souk,Rachidia,Rasidija,Rašidija,Rāšīdīja,alrshydyt,alrshydyt‎,ar-Rachidiya,ar-Rachīdīya,la xi di ye,Эр-Рашидия,א-רשידיה,الرشيدية,الرشيدية‎,الرشیدیہ,拉希迪耶",
        "latitude": 31.9314,
        "longitude": -4.42663,
        "feature_class": "P",
        "feature_code": "PPLA3",
        "country_code": "MA",
        "admin1_code": 8,
        "admin2_code": 201,
        "admin3_code": 1320101051,
        "population": 92374,
        "dem": 1039,
        "timezone": "Africa/Casablanca",
        "modification_date": "2017-12-06",
        "createdAt": "2020-12-15T12:45:39.525Z",
        "updatedAt": "2020-12-15T12:45:39.525Z"
      },
      {
        "objectId": "hEtUwi990H",
        "geonameid": 2549263,
        "name": "Essaouira",
        "asciiname": "Essaouira",
        "alternatenames": "Amegdul,As Suwayrah,As-Sawira,As-Sawíra,As-Shawirah,Aş Şuwayrah,ESU,Ehs-Suvejra,Ehssuehjra,Es Suira,Es-Suvejra,Esauira,Essaouira,Essauira,Magador,Medino de Esauiro,Medino de Esaŭiro,Mogadar,Mogador,Savira,Suira,Suvayr,Szavira,Szavíra,alswyrt,as-Sawira,as-Ṣawīra,el-suvaira,es'sa'ura,esau-ila,essau~ira,mwghadwr,mwkadwr,suo wei la,swyrh,Ес-Сувейра,Эс-Сувейра,Эссуэйра,אסואירה,الصويرة,صویره,صویرہ,موغادور,موكادور,एस्साउरा,ელ-სუვაირა,エッサウィラ,索维拉,에사우이라",
        "latitude": 31.5125,
        "longitude": -9.77,
        "feature_class": "P",
        "feature_code": "PPLA3",
        "country_code": "MA",
        "admin1_code": 7,
        "admin2_code": 211,
        "admin3_code": 721101051,
        "population": 70634,
        "dem": 7,
        "timezone": "Africa/Casablanca",
        "modification_date": "2020-01-24",
        "createdAt": "2020-12-15T12:45:37.997Z",
        "updatedAt": "2020-12-15T12:45:37.997Z"
      },
      {
        "objectId": "iNTfo8JBV7",
        "geonameid": 2548885,
        "name": "Fès",
        "asciiname": "Fes",
        "alternatenames": "FEZ,Fes,Fez,Fès,fas,fezu,Фес,فاس,フェズ",
        "latitude": 34.03313,
        "longitude": -5.00028,
        "feature_class": "P",
        "feature_code": "PPLA",
        "country_code": "MA",
        "admin1_code": 3,
        "admin2_code": 231,
        "admin3_code": 1423101071,
        "population": 964891,
        "dem": 406,
        "timezone": "Africa/Casablanca",
        "modification_date": "2020-06-11",
        "createdAt": "2020-12-15T12:45:37.997Z",
        "updatedAt": "2020-12-15T12:45:37.997Z"
      },
      {
        "objectId": "nhIrr14siG",
        "geonameid": 2548880,
        "name": "Fès al Bali",
        "asciiname": "Fes al Bali",
        "alternatenames": "Fes al Bali,Fes le Vieux,Fes-l'Ancien,Fès al Bali,Fès le Vieux,Fès-l’Ancien,Medina,Old Fes",
        "latitude": 34.0701,
        "longitude": -4.95473,
        "feature_class": "P",
        "feature_code": "PPLX",
        "country_code": "MA",
        "admin1_code": 3,
        "admin2_code": 231,
        "population": 156000,
        "dem": 237,
        "timezone": "Africa/Casablanca",
        "modification_date": "2020-06-11",
        "createdAt": "2020-12-15T12:45:37.997Z",
        "updatedAt": "2020-12-15T12:45:37.997Z"
      },
      {
        "objectId": "Wv7mlz7HAc",
        "geonameid": 2548851,
        "name": "Figuig (Centre)",
        "asciiname": "Figuig (Centre)",
        "alternatenames": "Figuiq,Markaz Fikik,Markaz Fikīk,mrkz fkyk,مركز فكيك",
        "latitude": 32.10891,
        "longitude": -1.22855,
        "feature_class": "P",
        "feature_code": "PPL",
        "country_code": "MA",
        "admin1_code": 54,
        "population": 12516,
        "dem": 898,
        "timezone": "Africa/Casablanca",
        "modification_date": "2019-03-13",
        "createdAt": "2020-12-15T12:45:37.997Z",
        "updatedAt": "2020-12-15T12:45:37.997Z"
      },
      {
        "objectId": "VszB9dWqc8",
        "geonameid": 2548818,
        "name": "Fnidek",
        "asciiname": "Fnidek",
        "alternatenames": "Castillejos,Fnidek,Fnideq,Fnides,Los Castillejos,Фнидек",
        "latitude": 35.84906,
        "longitude": -5.35747,
        "feature_class": "P",
        "feature_code": "PPL",
        "country_code": "MA",
        "admin1_code": 1,
        "admin2_code": 571,
        "population": 53559,
        "dem": 21,
        "timezone": "Africa/Casablanca",
        "modification_date": "2018-08-06",
        "createdAt": "2020-12-15T12:45:37.997Z",
        "updatedAt": "2020-12-15T12:45:37.997Z"
      },
      {
        "objectId": "EE7tNyTTgM",
        "geonameid": 11071897,
        "name": "Gleibet El Foula",
        "asciiname": "Gleibet El Foula",
        "latitude": 23.43868,
        "longitude": -13.74664,
        "feature_class": "P",
        "feature_code": "PPL",
        "country_code": "MA",
        "admin1_code": 12,
        "admin2_code": 391,
        "admin3_code": 139105032,
        "population": 275,
        "dem": 346,
        "timezone": "Africa/Casablanca",
        "modification_date": "2016-11-04",
        "createdAt": "2020-12-15T12:45:39.525Z",
        "updatedAt": "2020-12-15T12:45:39.525Z"
      },
      {
        "objectId": "XFmYAiGJEy",
        "geonameid": 2548526,
        "name": "Guelmim",
        "asciiname": "Guelmim",
        "alternatenames": "GLN,Gelmima,Gelmimas,Gelmīma,Goulimine,Guelmim,Gulimin,Kulmim,Kulmīm,gai lei min,gelmim,gerumin,gulimimi,klmym,nglmym,Гулимин,Гулимин қаласы,Гулімін,كلميم,کلمیم,ڭلميم,გულიმიმი,ゲルミン,蓋勒敏,겔밈",
        "latitude": 28.98696,
        "longitude": -10.05738,
        "feature_class": "P",
        "feature_code": "PPLA",
        "country_code": "MA",
        "admin1_code": 10,
        "admin2_code": 261,
        "admin3_code": 326101031,
        "population": 98229,
        "dem": 301,
        "timezone": "Africa/Casablanca",
        "modification_date": "2019-12-04",
        "createdAt": "2020-12-15T12:45:37.997Z",
        "updatedAt": "2020-12-15T12:45:37.997Z"
      },
      {
        "objectId": "66vLLpmVxg",
        "geonameid": 9645313,
        "name": "Gueltat Zemmour",
        "asciiname": "Gueltat Zemmour",
        "latitude": 25.14276,
        "longitude": -12.37168,
        "feature_class": "P",
        "feature_code": "PPL",
        "country_code": "MA",
        "admin1_code": 11,
        "admin2_code": 121,
        "admin3_code": 212103012,
        "population": 6740,
        "dem": 419,
        "timezone": "Africa/Casablanca",
        "modification_date": "2016-11-04",
        "createdAt": "2020-12-15T12:45:39.525Z",
        "updatedAt": "2020-12-15T12:45:39.525Z"
      },
      {
        "objectId": "odMrk5CsBd",
        "geonameid": 2548489,
        "name": "Guercif",
        "asciiname": "Guercif",
        "alternatenames": "Garsif,Guercif",
        "latitude": 34.22568,
        "longitude": -3.35361,
        "feature_class": "P",
        "feature_code": "PPLA3",
        "country_code": "MA",
        "admin1_code": 3,
        "admin2_code": 561,
        "admin3_code": 1556101031,
        "population": 57544,
        "dem": 367,
        "timezone": "Africa/Casablanca",
        "modification_date": "2016-11-02",
        "createdAt": "2020-12-15T12:45:37.997Z",
        "updatedAt": "2020-12-15T12:45:37.997Z"
      },
      {
        "objectId": "Yt1PGvGY62",
        "geonameid": 7909712,
        "name": "Hassilabied",
        "asciiname": "Hassilabied",
        "alternatenames": "Hassi Labied,Hassilabied,Khassilabied,Хассилабиед",
        "latitude": 31.13448,
        "longitude": -4.02623,
        "feature_class": "P",
        "feature_code": "PPL",
        "country_code": "MA",
        "admin1_code": 48,
        "population": 150,
        "dem": 710,
        "timezone": "Africa/Casablanca",
        "modification_date": "2018-04-25",
        "createdAt": "2020-12-15T12:45:39.525Z",
        "updatedAt": "2020-12-15T12:45:39.525Z"
      },
      {
        "objectId": "AqK1Nb0yzl",
        "geonameid": 2543394,
        "name": "Ifrane",
        "asciiname": "Ifrane",
        "alternatenames": "Ifran,Ifrane,Lfrane,Ифран",
        "latitude": 31.70217,
        "longitude": -6.3494,
        "feature_class": "P",
        "feature_code": "PPL",
        "country_code": "MA",
        "admin1_code": 5,
        "population": 13000,
        "dem": 2019,
        "timezone": "Africa/Casablanca",
        "modification_date": "2017-10-04",
        "createdAt": "2020-12-15T12:45:37.997Z",
        "updatedAt": "2020-12-15T12:45:37.997Z"
      },
      {
        "objectId": "iW7JymzCoB",
        "geonameid": 2546917,
        "name": "Ifrane",
        "asciiname": "Ifrane",
        "alternatenames": "Ifran,Ifranas,Ifrane,afran,ipeulan,yi fu lan,Ифран,איפראן,إفران,افران,伊夫兰,이프란",
        "latitude": 33.52666,
        "longitude": -5.11019,
        "feature_class": "P",
        "feature_code": "PPLA3",
        "country_code": "MA",
        "admin1_code": 3,
        "admin2_code": 271,
        "admin3_code": 1327101031,
        "population": 73782,
        "dem": 1648,
        "timezone": "Africa/Casablanca",
        "modification_date": "2018-05-18",
        "createdAt": "2020-12-15T12:45:37.997Z",
        "updatedAt": "2020-12-15T12:45:37.997Z"
      },
      {
        "objectId": "b6j7k5AceE",
        "geonameid": 11071896,
        "name": "Imlili",
        "asciiname": "Imlili",
        "alternatenames": "amlyly,إمليلي,امليلي",
        "latitude": 22.6558,
        "longitude": -15.60719,
        "feature_class": "P",
        "feature_code": "PPL",
        "country_code": "MA",
        "admin1_code": 12,
        "admin2_code": 391,
        "admin3_code": 139109032,
        "population": 2269,
        "dem": 230,
        "timezone": "Africa/Casablanca",
        "modification_date": "2020-05-07",
        "createdAt": "2020-12-15T12:45:39.525Z",
        "updatedAt": "2020-12-15T12:45:39.525Z"
      },
      {
        "objectId": "l51KSBmWAY",
        "geonameid": 2550898,
        "name": "Imzouren",
        "asciiname": "Imzouren",
        "alternatenames": "Ain Zoren,Amzourhen-Khemis-Mrabten,Amzourhèn-Khémis-Mrabtèn,Aïn Zorèn,Eimoren,Einzoren,Einzorene,Imsouren,Imzouren,Imzourene,Imzoûrene,Izourene",
        "latitude": 35.14637,
        "longitude": -3.85063,
        "feature_class": "P",
        "feature_code": "PPLA3",
        "country_code": "MA",
        "admin1_code": 1,
        "admin2_code": 51,
        "admin3_code": 1505101051,
        "population": 40000,
        "dem": 77,
        "timezone": "Africa/Casablanca",
        "modification_date": "2016-11-29",
        "createdAt": "2020-12-15T12:45:37.997Z",
        "updatedAt": "2020-12-15T12:45:37.997Z"
      },
      {
        "objectId": "j8FrCvWKyQ",
        "geonameid": 2596325,
        "name": "Jebel Tiskaouine",
        "asciiname": "Jebel Tiskaouine",
        "latitude": 31.02722,
        "longitude": -5.11643,
        "feature_class": "P",
        "feature_code": "PPL",
        "country_code": "MA",
        "admin1_code": 8,
        "population": 1197,
        "dem": 1025,
        "timezone": "Africa/Casablanca",
        "modification_date": "2017-10-05",
        "createdAt": "2020-12-15T12:45:39.525Z",
        "updatedAt": "2020-12-15T12:45:39.525Z"
      },
      {
        "objectId": "gZh6gUXUrV",
        "geonameid": 2545017,
        "name": "Jerada",
        "asciiname": "Jerada",
        "alternatenames": "Djerada,Dzherada,Jerada,Джерада",
        "latitude": 34.31,
        "longitude": -2.16,
        "feature_class": "P",
        "feature_code": "PPLA3",
        "country_code": "MA",
        "admin1_code": 2,
        "admin2_code": 275,
        "admin3_code": 827501171,
        "population": 43696,
        "dem": 1045,
        "timezone": "Africa/Casablanca",
        "modification_date": "2016-11-02",
        "createdAt": "2020-12-15T12:45:37.997Z",
        "updatedAt": "2020-12-15T12:45:37.997Z"
      },
      {
        "objectId": "WEJ7Muk1Kb",
        "geonameid": 2544720,
        "name": "Kasba Tadla",
        "asciiname": "Kasba Tadla",
        "alternatenames": "Kasba Tadla,Kasbah Tadla,Tadla",
        "latitude": 32.5977,
        "longitude": -6.26844,
        "feature_class": "P",
        "feature_code": "PPLA3",
        "country_code": "MA",
        "admin1_code": 5,
        "admin2_code": 91,
        "admin3_code": 1209101071,
        "population": 41199,
        "dem": 499,
        "timezone": "Africa/Casablanca",
        "modification_date": "2016-11-02",
        "createdAt": "2020-12-15T12:45:37.997Z",
        "updatedAt": "2020-12-15T12:45:37.997Z"
      },
      {
        "objectId": "kSfmfhTvDY",
        "geonameid": 2549981,
        "name": "Kelaat Mgouna",
        "asciiname": "Kelaat Mgouna",
        "alternatenames": "El Kelaa,El Kelaa des Mgouna,Kelaat Mgouna,Kelaat Mguna,Qala'at Mgouna,Qala’at Mgouna,Келаат Мгуна",
        "latitude": 31.24573,
        "longitude": -6.1326,
        "feature_class": "P",
        "feature_code": "PPL",
        "country_code": "MA",
        "admin1_code": 8,
        "admin2_code": 577,
        "admin3_code": 440101051,
        "population": 14190,
        "dem": 1431,
        "timezone": "Africa/Casablanca",
        "modification_date": "2018-06-14",
        "createdAt": "2020-12-15T12:45:37.997Z",
        "updatedAt": "2020-12-15T12:45:37.997Z"
      },
      {
        "objectId": "sM0AYpbAQx",
        "geonameid": 2544571,
        "name": "Kenitra",
        "asciiname": "Kenitra",
        "alternatenames": "Al Qunaytirah,Al Qunayţirah,Al-Kunajtira,Kenitra,Kenitro,Khenifra,Kénitra,Lyautey,Mina Hassan Tani,NNA,Port Laoti,Port-Lyautey,Ville de Kenitra,alqnytrt,gai ni te la,keniteula,kenitora,qnytrh,Кенитра,Кенитра қаласы,Кенітра,אל-קניטרה,القنيطرة,قنیطره,კენიტრა,ケニトラ,蓋尼特拉,케니트라",
        "latitude": 34.26101,
        "longitude": -6.5802,
        "feature_class": "P",
        "feature_code": "PPLA",
        "country_code": "MA",
        "admin1_code": 4,
        "admin2_code": 281,
        "admin3_code": 528101011,
        "population": 366570,
        "dem": 13,
        "timezone": "Africa/Casablanca",
        "modification_date": "2019-09-05",
        "createdAt": "2020-12-15T12:45:37.997Z",
        "updatedAt": "2020-12-15T12:45:37.997Z"
      },
      {
        "objectId": "zPfMnlVGbb",
        "geonameid": 2558470,
        "name": "Khemisset",
        "asciiname": "Khemisset",
        "alternatenames": "Al Khmissat,Khemisset,Kimisset",
        "latitude": 33.82404,
        "longitude": -6.06627,
        "feature_class": "P",
        "feature_code": "PPLA3",
        "country_code": "MA",
        "admin1_code": 4,
        "admin2_code": 291,
        "admin3_code": 1029101011,
        "population": 106991,
        "dem": 451,
        "timezone": "Africa/Casablanca",
        "modification_date": "2016-11-02",
        "createdAt": "2020-12-15T12:45:37.997Z",
        "updatedAt": "2020-12-15T12:45:37.997Z"
      },
      {
        "objectId": "8jgxOHxrPV",
        "geonameid": 2544333,
        "name": "Khenifra",
        "asciiname": "Khenifra",
        "alternatenames": "Chenifra,Chunajfira,Jenifra,Khenifra,Khénifra,Xnifra,hai ni fu la,khnyfrh,khnyfrt,Хенифра,خنيفرة,خنیفره,خنیفرہ,海尼夫拉",
        "latitude": 32.93492,
        "longitude": -5.66167,
        "feature_class": "P",
        "feature_code": "PPLA3",
        "country_code": "MA",
        "admin1_code": 5,
        "admin2_code": 301,
        "admin3_code": 1330101011,
        "population": 73906,
        "dem": 868,
        "timezone": "Africa/Casablanca",
        "modification_date": "2016-11-02",
        "createdAt": "2020-12-15T12:45:37.997Z",
        "updatedAt": "2020-12-15T12:45:37.997Z"
      },
      {
        "objectId": "52Lfzd1hBK",
        "geonameid": 2544248,
        "name": "Khouribga",
        "asciiname": "Khouribga",
        "alternatenames": "Khouribga,Khouribja,Kouriga,Kourigha,khrybkt,خريبكة",
        "latitude": 32.88108,
        "longitude": -6.9063,
        "feature_class": "P",
        "feature_code": "PPLA3",
        "country_code": "MA",
        "admin1_code": 5,
        "admin2_code": 311,
        "admin3_code": 631101071,
        "population": 167673,
        "dem": 804,
        "timezone": "Africa/Casablanca",
        "modification_date": "2016-11-02",
        "createdAt": "2020-12-15T12:45:37.997Z",
        "updatedAt": "2020-12-15T12:45:37.997Z"
      },
      {
        "objectId": "mkogaN7VRn",
        "geonameid": 2544001,
        "name": "Ksar El Kebir",
        "asciiname": "Ksar El Kebir",
        "alternatenames": "Alcazarquebir,Alcazarquivir,Alcazquivir,El Ksar El Kbir,El Ksar El Kebir,Ksar El Kebir",
        "latitude": 35.00044,
        "longitude": -5.90378,
        "feature_class": "P",
        "feature_code": "PPL",
        "country_code": "MA",
        "admin1_code": 1,
        "admin2_code": 331,
        "population": 108753,
        "dem": 18,
        "timezone": "Africa/Casablanca",
        "modification_date": "2016-11-04",
        "createdAt": "2020-12-15T12:45:37.997Z",
        "updatedAt": "2020-12-15T12:45:37.997Z"
      },
      {
        "objectId": "sxURocVVMp",
        "geonameid": 2543549,
        "name": "Larache",
        "asciiname": "Larache",
        "alternatenames": "Al `Ara'ish,Al ‘Arā’īsh,Al-Araisz,El Aaraich,El Araish,Larache,Larasas,Larash,Larasha,Laraso,Laraxe,Laraŝo,Larašas,Larraix,Lavache,araishu,la la shen,la rach,lalasyu,Лараш,Лараша,לראצה,العرائش,عرائش,عرایش,ลารัช,アライシュ,拉臘什,라라슈",
        "latitude": 35.19321,
        "longitude": -6.15572,
        "feature_class": "P",
        "feature_code": "PPLA3",
        "country_code": "MA",
        "admin1_code": 1,
        "admin2_code": 331,
        "admin3_code": 1633101031,
        "population": 109294,
        "dem": 38,
        "timezone": "Africa/Casablanca",
        "modification_date": "2016-11-02",
        "createdAt": "2020-12-15T12:45:37.997Z",
        "updatedAt": "2020-12-15T12:45:37.997Z"
      },
      {
        "objectId": "7gt4JWrfwb",
        "geonameid": 11396027,
        "name": "Mahroun",
        "asciiname": "Mahroun",
        "latitude": 35.04349,
        "longitude": -5.23378,
        "feature_class": "P",
        "feature_code": "PPL",
        "country_code": "MA",
        "population": 600,
        "elevation": 1200,
        "dem": 910,
        "timezone": "Africa/Casablanca",
        "modification_date": "2016-12-24",
        "createdAt": "2020-12-15T12:45:39.525Z",
        "updatedAt": "2020-12-15T12:45:39.525Z"
      },
      {
        "objectId": "MpyyY6o5Q7",
        "geonameid": 2542997,
        "name": "Marrakesh",
        "asciiname": "Marrakesh",
        "alternatenames": "Marakes,Marakesh,Marakeso,Marakeŝo,Marakeš,Maraksh,Marrakech,Marrakes,Marrakesch,Marrakesh,Marrakesz,Marraqueix,Marraquexe,Marràqueix,Marrákes,Marrákeš,Merrakex,Morocco City,RAK,ma la ke shen,marakeshu,mraksh,Маракеш,Марракеш,مراكش,ⴰⵎⵓⵔⴰⴽⵓⵛ,マラケシュ,马拉喀什",
        "latitude": 31.63416,
        "longitude": -7.99994,
        "feature_class": "P",
        "feature_code": "PPLA",
        "country_code": "MA",
        "admin1_code": 7,
        "admin2_code": 351,
        "admin3_code": 735101071,
        "population": 839296,
        "dem": 457,
        "timezone": "Africa/Casablanca",
        "modification_date": "2016-11-03",
        "createdAt": "2020-12-15T12:45:37.997Z",
        "updatedAt": "2020-12-15T12:45:37.997Z"
      },
      {
        "objectId": "ArY4xVihFF",
        "geonameid": 2542987,
        "name": "Martil",
        "asciiname": "Martil",
        "alternatenames": "Martil,Rio Martin,Rio Martine,Río Martín,Wad Martin,Wād Martīn",
        "latitude": 35.61662,
        "longitude": -5.27522,
        "feature_class": "P",
        "feature_code": "PPLA3",
        "country_code": "MA",
        "admin1_code": 1,
        "admin2_code": 571,
        "admin3_code": 1657101031,
        "population": 39738,
        "dem": 5,
        "timezone": "Africa/Casablanca",
        "modification_date": "2016-11-02",
        "createdAt": "2020-12-15T12:45:37.997Z",
        "updatedAt": "2020-12-15T12:45:37.997Z"
      },
      {
        "objectId": "6dLRDWkVQE",
        "geonameid": 2542444,
        "name": "Marzouga",
        "asciiname": "Marzouga",
        "alternatenames": "Marzouga,Merzouga,Merzuga,Мерзуга",
        "latitude": 31.09914,
        "longitude": -4.01304,
        "feature_class": "P",
        "feature_code": "PPL",
        "country_code": "MA",
        "admin1_code": 8,
        "population": 500,
        "dem": 699,
        "timezone": "Africa/Casablanca",
        "modification_date": "2018-04-25",
        "createdAt": "2020-12-15T12:45:37.997Z",
        "updatedAt": "2020-12-15T12:45:37.997Z"
      },
      {
        "objectId": "QYdWfyjdq8",
        "geonameid": 2542866,
        "name": "Mechraa Bel Ksiri",
        "asciiname": "Mechraa Bel Ksiri",
        "alternatenames": "Ksiri,Mechra Belqsiri,Mechra al Ksiri,Mechra-bel-Kairi,Mechraa Bel Ksiri,Mechrá Belqsiri",
        "latitude": 34.57373,
        "longitude": -5.95585,
        "feature_class": "P",
        "feature_code": "PPLA3",
        "country_code": "MA",
        "admin1_code": 4,
        "admin2_code": 481,
        "admin3_code": 548101071,
        "population": 27802,
        "dem": 20,
        "timezone": "Africa/Casablanca",
        "modification_date": "2016-11-29",
        "createdAt": "2020-12-15T12:45:37.997Z",
        "updatedAt": "2020-12-15T12:45:37.997Z"
      },
      {
        "objectId": "8BY1Q09zzn",
        "geonameid": 2542715,
        "name": "Meknès",
        "asciiname": "Meknes",
        "alternatenames": "MEK,Mekinez,Meknes,Meknès,mei ke nei si,mekunesu,mknas,mqns,Мекнес,מקנס,مكناس,مکناس,ⴰⵎⴽⵏⴰⵙ,メクネス,梅克内斯",
        "latitude": 33.89352,
        "longitude": -5.54727,
        "feature_class": "P",
        "feature_code": "PPLA2",
        "country_code": "MA",
        "admin1_code": 3,
        "admin2_code": 61,
        "admin3_code": 1306101011,
        "population": 545705,
        "dem": 531,
        "timezone": "Africa/Casablanca",
        "modification_date": "2017-02-01",
        "createdAt": "2020-12-15T12:45:37.997Z",
        "updatedAt": "2020-12-15T12:45:37.997Z"
      },
      {
        "objectId": "KjdXl5hiDC",
        "geonameid": 2565267,
        "name": "Mhamid",
        "asciiname": "Mhamid",
        "alternatenames": "Mhamid,Mkhamid,Мхамид",
        "latitude": 29.82,
        "longitude": -5.72,
        "feature_class": "P",
        "feature_code": "PPL",
        "country_code": "MA",
        "admin1_code": 8,
        "population": 10000,
        "dem": 550,
        "timezone": "Africa/Casablanca",
        "modification_date": "2017-10-04",
        "createdAt": "2020-12-15T12:45:37.997Z",
        "updatedAt": "2020-12-15T12:45:37.997Z"
      },
      {
        "objectId": "gCnWsESJPW",
        "geonameid": 2542230,
        "name": "Midar",
        "asciiname": "Midar",
        "alternatenames": "Arba Laazib Midar,Azib de Midar,El Arba de Midar,Midar,Soko Arbaa Laazib Midar,Мидар",
        "latitude": 34.94025,
        "longitude": -3.53311,
        "feature_class": "P",
        "feature_code": "PPLA3",
        "country_code": "MA",
        "admin1_code": 2,
        "admin2_code": 381,
        "admin3_code": 838109132,
        "population": 10229,
        "dem": 388,
        "timezone": "Africa/Casablanca",
        "modification_date": "2018-05-21",
        "createdAt": "2020-12-15T12:45:37.997Z",
        "updatedAt": "2020-12-15T12:45:37.997Z"
      },
      {
        "objectId": "TWDqfwhMpM",
        "geonameid": 2542227,
        "name": "Midelt",
        "asciiname": "Midelt",
        "alternatenames": "Midelt",
        "latitude": 32.6852,
        "longitude": -4.74512,
        "feature_class": "P",
        "feature_code": "PPLA3",
        "country_code": "MA",
        "admin1_code": 5,
        "admin2_code": 301,
        "admin3_code": 1330101031,
        "population": 45159,
        "dem": 1462,
        "timezone": "Africa/Casablanca",
        "modification_date": "2016-11-02",
        "createdAt": "2020-12-15T12:45:37.997Z",
        "updatedAt": "2020-12-15T12:45:37.997Z"
      },
      {
        "objectId": "hRvhfPuA1N",
        "geonameid": 8987072,
        "name": "Mnoud",
        "asciiname": "Mnoud",
        "alternatenames": "Nekour",
        "latitude": 35.05898,
        "longitude": -3.82762,
        "feature_class": "P",
        "feature_code": "PPL",
        "country_code": "MA",
        "admin1_code": 1,
        "admin2_code": 51,
        "admin3_code": 1505105192,
        "population": 500,
        "elevation": 185,
        "dem": 191,
        "timezone": "Africa/Casablanca",
        "modification_date": "2016-11-02",
        "createdAt": "2020-12-15T12:45:39.525Z",
        "updatedAt": "2020-12-15T12:45:39.525Z"
      },
      {
        "objectId": "4WAivDhoMX",
        "geonameid": 2542051,
        "name": "Mohammedia",
        "asciiname": "Mohammedia",
        "alternatenames": "Al Muhammadiyah,Al Muḩammadīyah,Al-Muhammadijja,Fadalah,Faḑālah,Fdala,Fedala,Fedalah,Fedhala,Mohamedija,Mohamedio,Mohammadia,Mohammedia,Mohammédia,Mokhammedija,Muhammediye,Məhəmmədiyyə,Sedala,alhrawyyn,almhmdyt,mhmdyh,mohamedia,mu han mo di ye,Мохаммедия,المحمدية,الهراويين,محمدیه,محمدیہ,穆罕默迪耶,모하메디아",
        "latitude": 33.68607,
        "longitude": -7.38298,
        "feature_class": "P",
        "feature_code": "PPLA3",
        "country_code": "MA",
        "admin1_code": 6,
        "admin2_code": 371,
        "admin3_code": 937101011,
        "population": 187708,
        "dem": 29,
        "timezone": "Africa/Casablanca",
        "modification_date": "2018-12-21",
        "createdAt": "2020-12-15T12:45:37.997Z",
        "updatedAt": "2020-12-15T12:45:37.997Z"
      },
      {
        "objectId": "myL5MlyPB3",
        "geonameid": 8739768,
        "name": "Mosquée",
        "asciiname": "Mosquee",
        "latitude": 34.80622,
        "longitude": -2.41297,
        "feature_class": "P",
        "feature_code": "PPL",
        "country_code": "MA",
        "population": 3150,
        "elevation": 800,
        "dem": 799,
        "timezone": "Africa/Casablanca",
        "modification_date": "2014-03-14",
        "createdAt": "2020-12-15T12:45:39.525Z",
        "updatedAt": "2020-12-15T12:45:39.525Z"
      },
      {
        "objectId": "ErFrC22uJj",
        "geonameid": 2541479,
        "name": "Nador",
        "asciiname": "Nador",
        "alternatenames": "NDR,Nador,Nadora,Nadoras,Nnadur,Nnaḍur,Nādora,Villa Nador,alnazwr,na zu er,nad xr,nadoleu,nazwr,Надор,الناظور,ناظور,นาดอร์,納祖爾,나도르",
        "latitude": 35.16813,
        "longitude": -2.93352,
        "feature_class": "P",
        "feature_code": "PPLA3",
        "country_code": "MA",
        "admin1_code": 2,
        "admin2_code": 381,
        "admin3_code": 838101051,
        "population": 129260,
        "dem": 19,
        "timezone": "Africa/Casablanca",
        "modification_date": "2016-11-02",
        "createdAt": "2020-12-15T12:45:37.997Z",
        "updatedAt": "2020-12-15T12:45:37.997Z"
      },
      {
        "objectId": "d8ypxanVrJ",
        "geonameid": 2541068,
        "name": "Oualidia",
        "asciiname": "Oualidia",
        "alternatenames": "El Oualidia,Kasba Oualidia,Koudia Oualidia,Oualidiya,Qasbah al Walidiyah,Qaşbah al Walīdīyah,Qualidia,Ualidija,Уалидия",
        "latitude": 32.73372,
        "longitude": -9.03059,
        "feature_class": "P",
        "feature_code": "PPL",
        "country_code": "MA",
        "admin1_code": 6,
        "admin2_code": 181,
        "population": 5826,
        "dem": 51,
        "timezone": "Africa/Casablanca",
        "modification_date": "2018-08-15",
        "createdAt": "2020-12-15T12:45:37.997Z",
        "updatedAt": "2020-12-15T12:45:37.997Z"
      },
      {
        "objectId": "RsR4Ek1Ya7",
        "geonameid": 2540850,
        "name": "Ouarzazat",
        "asciiname": "Ouarzazat",
        "alternatenames": "OZZ,Ouarzazat,Ouarzazate,Ouarzazte,Ouorzazate,Uarzazat,Uarzazatas,Varzazat,Warzazat,Warzāzāt,wrzazat,wrzzat,Варзазат,Уарзазат,ورزازات,ورززات",
        "latitude": 30.91894,
        "longitude": -6.89341,
        "feature_class": "P",
        "feature_code": "PPLA2",
        "country_code": "MA",
        "admin1_code": 8,
        "admin2_code": 401,
        "population": 57245,
        "dem": 1113,
        "timezone": "Africa/Casablanca",
        "modification_date": "2018-04-25",
        "createdAt": "2020-12-15T12:45:37.997Z",
        "updatedAt": "2020-12-15T12:45:37.997Z"
      },
      {
        "objectId": "KPaXUsi1Vx",
        "geonameid": 2540689,
        "name": "Oued Zem",
        "asciiname": "Oued Zem",
        "alternatenames": "Wadi Zam,Wādī Zam,wad zm,wady zm,واد زم,وادي زم",
        "latitude": 32.8627,
        "longitude": -6.57359,
        "feature_class": "P",
        "feature_code": "PPLA3",
        "country_code": "MA",
        "admin1_code": 5,
        "admin2_code": 311,
        "admin3_code": 631101091,
        "population": 84910,
        "dem": 783,
        "timezone": "Africa/Casablanca",
        "modification_date": "2019-03-14",
        "createdAt": "2020-12-15T12:45:37.997Z",
        "updatedAt": "2020-12-15T12:45:37.997Z"
      },
      {
        "objectId": "LOzXpDsWoS",
        "geonameid": 2540810,
        "name": "Ouezzane",
        "asciiname": "Ouezzane",
        "alternatenames": "Ouazzane,Ouezzane,Quazzane,Uazan,Uazán,Wazzan",
        "latitude": 34.79584,
        "longitude": -5.57849,
        "feature_class": "P",
        "feature_code": "PPLA2",
        "country_code": "MA",
        "admin1_code": 1,
        "admin2_code": 405,
        "population": 58684,
        "dem": 306,
        "timezone": "Africa/Casablanca",
        "modification_date": "2016-11-29",
        "createdAt": "2020-12-15T12:45:37.997Z",
        "updatedAt": "2020-12-15T12:45:37.997Z"
      },
      {
        "objectId": "o7gKMFnJsR",
        "geonameid": 2540483,
        "name": "Oujda-Angad",
        "asciiname": "Oujda-Angad",
        "alternatenames": "OUD,Oudja,Oudjda,Ouja,Oujda,Oujda-Angad,Ucda,Udzda,Udzhda,Udžda,Ugda,Ujda,Uĝda,Wadzda,Wadżda,Wejda,ujida,wgdh,wjdh,wjdt,wjdt-anjad,wjdt-ankad,wu ji da,Уджда,Уджда қаласы,Уџда,וגדה,وجدة,وجدة-أنجاد,وجدة-أنكاد,وجده,وجدہ,ウジダ,乌季达,우지다",
        "latitude": 34.68139,
        "longitude": -1.90858,
        "feature_class": "P",
        "feature_code": "PPLA",
        "country_code": "MA",
        "admin1_code": 2,
        "admin2_code": 411,
        "admin3_code": 841101231,
        "population": 405253,
        "dem": 549,
        "timezone": "Africa/Casablanca",
        "modification_date": "2019-12-04",
        "createdAt": "2020-12-15T12:45:37.997Z",
        "updatedAt": "2020-12-15T12:45:37.997Z"
      },
      {
        "objectId": "BNLh8kM8bi",
        "geonameid": 2540468,
        "name": "Oukaïmedene",
        "asciiname": "Oukaimedene",
        "alternatenames": "Oukaimden,Oukaimeden,Oukaimedene,Oukaïmden,Oukaïmeden,Oukaïmedene,Oukkainrdem,Ukajmden,Укаймден",
        "latitude": 31.20603,
        "longitude": -7.86089,
        "feature_class": "P",
        "feature_code": "PPL",
        "country_code": "MA",
        "admin1_code": 7,
        "admin2_code": 351,
        "population": 4440,
        "dem": 2637,
        "timezone": "Africa/Casablanca",
        "modification_date": "2020-06-11",
        "createdAt": "2020-12-15T12:45:37.997Z",
        "updatedAt": "2020-12-15T12:45:37.997Z"
      },
      {
        "objectId": "BYuKcORcsH",
        "geonameid": 2539139,
        "name": "Oulad Tayeb",
        "asciiname": "Oulad Tayeb",
        "alternatenames": "Ulad Tajib,Улад Тайиб",
        "latitude": 33.94633,
        "longitude": -4.99509,
        "feature_class": "P",
        "feature_code": "PPLA3",
        "country_code": "MA",
        "admin1_code": 3,
        "admin2_code": 231,
        "admin3_code": 1423181012,
        "population": 500,
        "dem": 533,
        "timezone": "Africa/Casablanca",
        "modification_date": "2016-11-02",
        "createdAt": "2020-12-15T12:45:37.997Z",
        "updatedAt": "2020-12-15T12:45:37.997Z"
      },
      {
        "objectId": "lr3M707YHV",
        "geonameid": 2539134,
        "name": "Oulad Teïma",
        "asciiname": "Oulad Teima",
        "alternatenames": "Oulad Teima,Oulad Teïma,Ouled Teima",
        "latitude": 30.39467,
        "longitude": -9.20897,
        "feature_class": "P",
        "feature_code": "PPL",
        "country_code": "MA",
        "admin1_code": 9,
        "admin2_code": 541,
        "admin3_code": 454101091,
        "population": 66832,
        "dem": 129,
        "timezone": "Africa/Casablanca",
        "modification_date": "2020-06-11",
        "createdAt": "2020-12-15T12:45:37.997Z",
        "updatedAt": "2020-12-15T12:45:37.997Z"
      },
      {
        "objectId": "YdxvZx33Y9",
        "geonameid": 8629078,
        "name": "Ouled Khlifa",
        "asciiname": "Ouled Khlifa",
        "alternatenames": "Ulad Khlifa,Улад Хлифа",
        "latitude": 33.94265,
        "longitude": -5.00153,
        "feature_class": "P",
        "feature_code": "PPL",
        "country_code": "MA",
        "population": 200,
        "dem": 539,
        "timezone": "Africa/Casablanca",
        "modification_date": "2013-10-16",
        "createdAt": "2020-12-15T12:45:39.525Z",
        "updatedAt": "2020-12-15T12:45:39.525Z"
      },
      {
        "objectId": "WyjA0rj7oE",
        "geonameid": 2538898,
        "name": "Oulmes",
        "asciiname": "Oulmes",
        "alternatenames": "Oulmes,Oulmes-Les Thermes,Oulmès,Oulmès-Les Thermes,Ul'mes,awlmas,wlmas,Ульмес,أولماس,ولماس",
        "latitude": 33.42585,
        "longitude": -6.00137,
        "feature_class": "P",
        "feature_code": "PPLA3",
        "country_code": "MA",
        "admin1_code": 4,
        "admin2_code": 291,
        "admin3_code": 1029105112,
        "population": 19014,
        "dem": 1175,
        "timezone": "Africa/Casablanca",
        "modification_date": "2020-01-11",
        "createdAt": "2020-12-15T12:45:37.997Z",
        "updatedAt": "2020-12-15T12:45:37.997Z"
      },
      {
        "objectId": "ZZ1gN7RKhJ",
        "geonameid": 2538475,
        "name": "Rabat",
        "asciiname": "Rabat",
        "alternatenames": "RBA,Raba,Rabat,Rabata,Rabatas,Rabato,Rabatum,Rabot,Rabāt,Rabāta,Rampat,Rbat,Rbaṭ,alrbat,la ba,la ba te,labateu,raba t,rabat,rabata,rabato,rabota,rapat,rbat,Ραμπάτ,Рабат,Ռաբատ,ראבאט,רבאט,الرباط,رابات,ربات,رباط,ڕەبات,रबाट,रबात,রাবাত,ਰਬਾਤ,ରବୋଟ,ரபாத்,ราบัต,ར་བ་ཐ།,ར་བ་ཐེ།,რაბატი,ራባት,ラバト,剌八,拉巴特,라바트",
        "latitude": 34.01325,
        "longitude": -6.83255,
        "feature_class": "P",
        "feature_code": "PPLC",
        "country_code": "MA",
        "admin1_code": 4,
        "admin2_code": 421,
        "population": 1655753,
        "dem": 46,
        "timezone": "Africa/Casablanca",
        "modification_date": "2019-09-05",
        "createdAt": "2020-12-15T12:45:37.997Z",
        "updatedAt": "2020-12-15T12:45:37.997Z"
      },
      {
        "objectId": "jhfp7u37qK",
        "geonameid": 2538027,
        "name": "Reçani",
        "asciiname": "Recani",
        "alternatenames": "Recani,Reçani,Risani,Rissani,Рисани",
        "latitude": 31.28318,
        "longitude": -4.26565,
        "feature_class": "P",
        "feature_code": "PPL",
        "country_code": "MA",
        "admin1_code": 8,
        "population": 20469,
        "dem": 761,
        "timezone": "Africa/Casablanca",
        "modification_date": "2020-06-11",
        "createdAt": "2020-12-15T12:45:37.997Z",
        "updatedAt": "2020-12-15T12:45:37.997Z"
      },
      {
        "objectId": "uGhmvczr3E",
        "geonameid": 2537881,
        "name": "Safi",
        "asciiname": "Safi",
        "alternatenames": "Asafi,Asfi,SFI,Safi,Safim,Safí,Sáfí,asfy,asfy  mraksh,sa fei,safi,sapi,Сафи,Сафі,Սաֆի,סאפי,آسفي,اسفی,اسفی، مراکش,საფი,ⴰⵙⴼⵉ,サフィ,薩非,사피",
        "latitude": 32.29939,
        "longitude": -9.23718,
        "feature_class": "P",
        "feature_code": "PPLA2",
        "country_code": "MA",
        "admin1_code": 7,
        "admin2_code": 431,
        "admin3_code": 1143101031,
        "population": 288163,
        "dem": 45,
        "timezone": "Africa/Casablanca",
        "modification_date": "2019-09-05",
        "createdAt": "2020-12-15T12:45:37.997Z",
        "updatedAt": "2020-12-15T12:45:37.997Z"
      },
      {
        "objectId": "rWsol3FHEy",
        "geonameid": 2537802,
        "name": "Saidia",
        "asciiname": "Saidia",
        "alternatenames": "Saida,Saidia,Saidia du Kiss,Saidija,Saïda,Saïdia,Saïdia du Kiss,Саидия",
        "latitude": 35.08195,
        "longitude": -2.22897,
        "feature_class": "P",
        "feature_code": "PPL",
        "country_code": "MA",
        "admin1_code": 2,
        "population": 3871,
        "dem": 4,
        "timezone": "Africa/Casablanca",
        "modification_date": "2018-08-06",
        "createdAt": "2020-12-15T12:45:37.997Z",
        "updatedAt": "2020-12-15T12:45:37.997Z"
      },
      {
        "objectId": "422TzVbiRG",
        "geonameid": 2537763,
        "name": "Sale",
        "asciiname": "Sale",
        "alternatenames": "Sala,Sale,Sali,Sallee,Salé,Sla,Slà,sla,Сале,سلا",
        "latitude": 34.0531,
        "longitude": -6.79846,
        "feature_class": "P",
        "feature_code": "PPL",
        "country_code": "MA",
        "admin1_code": 4,
        "admin2_code": 441,
        "population": 903485,
        "dem": 34,
        "timezone": "Africa/Casablanca",
        "modification_date": "2016-11-04",
        "createdAt": "2020-12-15T12:45:37.997Z",
        "updatedAt": "2020-12-15T12:45:37.997Z"
      },
      {
        "objectId": "TQPJgZ9Xoo",
        "geonameid": 10920963,
        "name": "Salé Al Jadida",
        "asciiname": "Sale Al Jadida",
        "latitude": 33.99722,
        "longitude": -6.74047,
        "feature_class": "P",
        "feature_code": "PPL",
        "country_code": "MA",
        "admin1_code": 4,
        "population": 200000,
        "dem": 119,
        "timezone": "Africa/Casablanca",
        "modification_date": "2019-12-19",
        "createdAt": "2020-12-15T12:45:39.525Z",
        "updatedAt": "2020-12-15T12:45:39.525Z"
      },
      {
        "objectId": "AuYqt42LEw",
        "geonameid": 2537545,
        "name": "Sefrou",
        "asciiname": "Sefrou",
        "alternatenames": "Sefrou,Sefru,Sefrú",
        "latitude": 33.83186,
        "longitude": -4.828,
        "feature_class": "P",
        "feature_code": "PPLA3",
        "country_code": "MA",
        "admin1_code": 3,
        "admin2_code": 451,
        "admin3_code": 1445101091,
        "population": 65150,
        "dem": 809,
        "timezone": "Africa/Casablanca",
        "modification_date": "2016-11-02",
        "createdAt": "2020-12-15T12:45:37.997Z",
        "updatedAt": "2020-12-15T12:45:37.997Z"
      },
      {
        "objectId": "LvSOHWfROt",
        "geonameid": 2537406,
        "name": "Settat",
        "asciiname": "Settat",
        "alternatenames": "Azettad,Aẓeṭṭaḍ,Sattat,Setatas,Settat,sai ta te,setateu,sltat,stat,Сеттат,سطات,سلطات,სეტატი,塞塔特,세타트",
        "latitude": 33.00103,
        "longitude": -7.61662,
        "feature_class": "P",
        "feature_code": "PPLA2",
        "country_code": "MA",
        "admin1_code": 6,
        "admin2_code": 461,
        "admin3_code": 646101151,
        "population": 119082,
        "dem": 365,
        "timezone": "Africa/Casablanca",
        "modification_date": "2016-11-03",
        "createdAt": "2020-12-15T12:45:37.997Z",
        "updatedAt": "2020-12-15T12:45:37.997Z"
      },
      {
        "objectId": "MSi6CHsnry",
        "geonameid": 2526239,
        "name": "Setti Fatma",
        "asciiname": "Setti Fatma",
        "alternatenames": "Sette Fatna,Setti Fadma,Setti Fatma,Sti Fadma,Sti-Fadma,Zaouia Sti Fatma,Сти-Фадма",
        "latitude": 31.22508,
        "longitude": -7.67751,
        "feature_class": "P",
        "feature_code": "PPL",
        "country_code": "MA",
        "admin1_code": 7,
        "population": 22283,
        "dem": 1434,
        "timezone": "Africa/Casablanca",
        "modification_date": "2018-08-06",
        "createdAt": "2020-12-15T12:45:37.996Z",
        "updatedAt": "2020-12-15T12:45:37.996Z"
      },
      {
        "objectId": "upAF8AKdMG",
        "geonameid": 2536074,
        "name": "Sidi Bennour",
        "asciiname": "Sidi Bennour",
        "latitude": 32.65236,
        "longitude": -8.42769,
        "feature_class": "P",
        "feature_code": "PPLA3",
        "country_code": "MA",
        "admin1_code": 6,
        "admin2_code": 181,
        "admin3_code": 1118101071,
        "population": 40044,
        "dem": 182,
        "timezone": "Africa/Casablanca",
        "modification_date": "2016-11-02",
        "createdAt": "2020-12-15T12:45:37.997Z",
        "updatedAt": "2020-12-15T12:45:37.997Z"
      },
      {
        "objectId": "zXP5CzSDyJ",
        "geonameid": 2535760,
        "name": "Sidi Bouiachi",
        "asciiname": "Sidi Bouiachi",
        "alternatenames": "Sidi Bouiachi,Sidi Buiahi",
        "latitude": 35.04893,
        "longitude": -3.69927,
        "feature_class": "P",
        "feature_code": "PPLL",
        "country_code": "MA",
        "admin1_code": 54,
        "population": 160,
        "elevation": 450,
        "dem": 475,
        "timezone": "Africa/Casablanca",
        "modification_date": "2014-01-12",
        "createdAt": "2020-12-15T12:45:37.997Z",
        "updatedAt": "2020-12-15T12:45:37.997Z"
      },
      {
        "objectId": "6jovPmEHkQ",
        "geonameid": 2534515,
        "name": "Sidi Ifni",
        "asciiname": "Sidi Ifni",
        "alternatenames": "Ifni,SII,Sidi Ifni,Sidi Ifnis,Sidi-Ifni,Sidifni,sidiipeuni,sydy afny,Сиди Ифни,Сиди-Ифни,سيدي إفني,시디이프니",
        "latitude": 29.37975,
        "longitude": -10.17299,
        "feature_class": "P",
        "feature_code": "PPLA3",
        "country_code": "MA",
        "admin1_code": 9,
        "admin2_code": 581,
        "admin3_code": 458101031,
        "population": 20000,
        "dem": 44,
        "timezone": "Africa/Casablanca",
        "modification_date": "2016-11-02",
        "createdAt": "2020-12-15T12:45:37.997Z",
        "updatedAt": "2020-12-15T12:45:37.997Z"
      },
      {
        "objectId": "0VLCc3n8s5",
        "geonameid": 2533191,
        "name": "Sidi Qacem",
        "asciiname": "Sidi Qacem",
        "alternatenames": "Petitjean,Pettijean,Sidi Kacem,Sidi Qacem,Sidi Qasim,Sīdī Qāsim,sdy qasm,سدي قاسم",
        "latitude": 34.22149,
        "longitude": -5.70775,
        "feature_class": "P",
        "feature_code": "PPL",
        "country_code": "MA",
        "admin1_code": 4,
        "admin2_code": 481,
        "population": 74755,
        "dem": 83,
        "timezone": "Africa/Casablanca",
        "modification_date": "2016-11-04",
        "createdAt": "2020-12-15T12:45:37.997Z",
        "updatedAt": "2020-12-15T12:45:37.997Z"
      },
      {
        "objectId": "dvXwmwDfTo",
        "geonameid": 2532945,
        "name": "Sidi Slimane",
        "asciiname": "Sidi Slimane",
        "alternatenames": "Sidi Slamain,Sidi Sliman,Sidi Slimane,Sidi-Slimane,Сиди-Слимане",
        "latitude": 34.26479,
        "longitude": -5.92598,
        "feature_class": "P",
        "feature_code": "PPLA3",
        "country_code": "MA",
        "admin1_code": 4,
        "admin2_code": 281,
        "admin3_code": 528101071,
        "population": 79437,
        "dem": 37,
        "timezone": "Africa/Casablanca",
        "modification_date": "2016-11-02",
        "createdAt": "2020-12-15T12:45:37.997Z",
        "updatedAt": "2020-12-15T12:45:37.997Z"
      },
      {
        "objectId": "S2szLVb0OQ",
        "geonameid": 2532918,
        "name": "Sidi Smai’il",
        "asciiname": "Sidi Smai'il",
        "alternatenames": "Sidi Smai'il,Sidi Smail,Sidi Smaine,Sidi Smai’il,Sidi Smaïl,Sidi Smaïne,Sidi-Smain,Sidi-Smaïn,Zaouia Sidi Smain",
        "latitude": 32.82461,
        "longitude": -8.51122,
        "feature_class": "P",
        "feature_code": "PPL",
        "country_code": "MA",
        "admin1_code": 6,
        "population": 4279,
        "dem": 151,
        "timezone": "Africa/Casablanca",
        "modification_date": "2020-06-11",
        "createdAt": "2020-12-15T12:45:37.997Z",
        "updatedAt": "2020-12-15T12:45:37.997Z"
      },
      {
        "objectId": "kI1b51tSmm",
        "geonameid": 2532822,
        "name": "Sidi Yahia El Gharb",
        "asciiname": "Sidi Yahia El Gharb",
        "alternatenames": "Sidi Yahia El Gharb,Sidi Yahia al Gharb,Sidi Yahia del Garb,Sidi Yahia el Rharb,Sidi Yahya du Rharb,Sidi Yanya du Rharb,Sidi Yaya du Rhanb,Sïdi Yaya du Rhanb",
        "latitude": 34.30494,
        "longitude": -6.30404,
        "feature_class": "P",
        "feature_code": "PPLA3",
        "country_code": "MA",
        "admin1_code": 4,
        "admin2_code": 491,
        "admin3_code": 528101091,
        "population": 32202,
        "dem": 18,
        "timezone": "Africa/Casablanca",
        "modification_date": "2016-11-29",
        "createdAt": "2020-12-15T12:45:37.997Z",
        "updatedAt": "2020-12-15T12:45:37.997Z"
      },
      {
        "objectId": "CHZ0cYsrqX",
        "geonameid": 2562055,
        "name": "Skhirate",
        "asciiname": "Skhirate",
        "alternatenames": "Ac Ckhirat,Aç Çkhirat,Kasba Skira,Minaret de Skhirat,Skhirat,Skhirate",
        "latitude": 33.8527,
        "longitude": -7.03171,
        "feature_class": "P",
        "feature_code": "PPLA3",
        "country_code": "MA",
        "admin1_code": 4,
        "admin2_code": 501,
        "admin3_code": 1050101051,
        "population": 44850,
        "dem": 51,
        "timezone": "Africa/Casablanca",
        "modification_date": "2016-11-29",
        "createdAt": "2020-12-15T12:45:37.997Z",
        "updatedAt": "2020-12-15T12:45:37.997Z"
      },
      {
        "objectId": "1VGsmJVVMH",
        "geonameid": 2461874,
        "name": "Smara",
        "asciiname": "Smara",
        "alternatenames": "Asmara,Es-Semara,Es-Smara,Esmara,SMW,Semara,Smar,Smara,alsmart,seumala,si ma la,smarh,sumara,Смара,Смара қаласы,סמארה,السمارة,سماره,スマラ,斯马拉,스마라",
        "latitude": 26.73841,
        "longitude": -11.67194,
        "feature_class": "P",
        "feature_code": "PPL",
        "country_code": "MA",
        "cc2": "EH",
        "admin1_code": 11,
        "admin2_code": 221,
        "admin3_code": 322101011,
        "population": 42056,
        "dem": 188,
        "timezone": "Africa/Casablanca",
        "modification_date": "2017-07-08",
        "createdAt": "2020-12-15T12:45:37.996Z",
        "updatedAt": "2020-12-15T12:45:37.996Z"
      },
      {
        "objectId": "78zRDWkjMH",
        "geonameid": 2532394,
        "name": "Souq Larb’a al Gharb",
        "asciiname": "Souq Larb'a al Gharb",
        "alternatenames": "El Arba du Gharb,El Arba du Rharb,El Arbaa du Rharb,El Arboa du Rharb,Souk-el-Arba-du-Gharb,Souq Larb'a al Gharb,Souq Larb’a al Gharb",
        "latitude": 34.68664,
        "longitude": -6.00272,
        "feature_class": "P",
        "feature_code": "PPLA3",
        "country_code": "MA",
        "admin1_code": 4,
        "admin2_code": 281,
        "admin3_code": 528101111,
        "population": 44059,
        "dem": 37,
        "timezone": "Africa/Casablanca",
        "modification_date": "2016-11-29",
        "createdAt": "2020-12-15T12:45:37.997Z",
        "updatedAt": "2020-12-15T12:45:37.997Z"
      },
      {
        "objectId": "gjqc06cSGd",
        "geonameid": 2531877,
        "name": "Tafraout",
        "asciiname": "Tafraout",
        "alternatenames": "Tafraout,Tafraoute,Tafraut",
        "latitude": 29.72449,
        "longitude": -8.9747,
        "feature_class": "P",
        "feature_code": "PPLA3",
        "country_code": "MA",
        "admin1_code": 9,
        "admin2_code": 581,
        "admin3_code": 458101051,
        "population": 4924,
        "dem": 993,
        "timezone": "Africa/Casablanca",
        "modification_date": "2016-11-02",
        "createdAt": "2020-12-15T12:45:37.997Z",
        "updatedAt": "2020-12-15T12:45:37.997Z"
      },
      {
        "objectId": "sowN7AIRyn",
        "geonameid": 2568012,
        "name": "Taghazout",
        "asciiname": "Taghazout",
        "alternatenames": "Taghazout,Tarhazoute",
        "latitude": 30.54259,
        "longitude": -9.71115,
        "feature_class": "P",
        "feature_code": "PPLA3",
        "country_code": "MA",
        "admin1_code": 9,
        "admin2_code": 1,
        "admin3_code": 400105232,
        "population": 5233,
        "dem": 1,
        "timezone": "Africa/Casablanca",
        "modification_date": "2020-01-17",
        "createdAt": "2020-12-15T12:45:39.525Z",
        "updatedAt": "2020-12-15T12:45:39.525Z"
      },
      {
        "objectId": "WAus1dKK3m",
        "geonameid": 2531489,
        "name": "Tagzout",
        "asciiname": "Tagzout",
        "alternatenames": "Tagzout,Tagzut",
        "latitude": 35.05571,
        "longitude": -3.6916,
        "feature_class": "P",
        "feature_code": "PPLL",
        "country_code": "MA",
        "admin1_code": 54,
        "population": 150,
        "elevation": 500,
        "dem": 507,
        "timezone": "Africa/Casablanca",
        "modification_date": "2014-01-12",
        "createdAt": "2020-12-15T12:45:37.997Z",
        "updatedAt": "2020-12-15T12:45:37.997Z"
      },
      {
        "objectId": "TYY3PX7Bey",
        "geonameid": 2531480,
        "name": "Tahla",
        "asciiname": "Tahla",
        "alternatenames": "El Ayba Tahalla,Tahala,Tahla",
        "latitude": 34.04965,
        "longitude": -4.42162,
        "feature_class": "P",
        "feature_code": "PPLA3",
        "country_code": "MA",
        "admin1_code": 3,
        "admin2_code": 561,
        "admin3_code": 1556101071,
        "population": 25761,
        "dem": 606,
        "timezone": "Africa/Casablanca",
        "modification_date": "2016-11-29",
        "createdAt": "2020-12-15T12:45:37.997Z",
        "updatedAt": "2020-12-15T12:45:37.997Z"
      },
      {
        "objectId": "19hg0BvB4m",
        "geonameid": 2530241,
        "name": "Tan-Tan",
        "asciiname": "Tan-Tan",
        "alternatenames": "TTA,Tan-Tan,Tantan,Tantanas,tantan,Тан-Тан,طانطان,タンタン",
        "latitude": 28.43799,
        "longitude": -11.10321,
        "feature_class": "P",
        "feature_code": "PPLA2",
        "country_code": "MA",
        "admin1_code": 10,
        "admin2_code": 521,
        "population": 61924,
        "dem": 45,
        "timezone": "Africa/Casablanca",
        "modification_date": "2019-09-05",
        "createdAt": "2020-12-15T12:45:37.997Z",
        "updatedAt": "2020-12-15T12:45:37.997Z"
      },
      {
        "objectId": "yULxQCcx1t",
        "geonameid": 2530335,
        "name": "Tangier",
        "asciiname": "Tangier",
        "alternatenames": "TNG,Tanger,Tangeri,Tangero,Tangier,Tangiers,Tanzher,Tanĝero,Tingis,Tànger,Tánger,Tânger,tan ji ya,tnjt,Тангер,Танжер,طنجة,坦幾亞",
        "latitude": 35.76727,
        "longitude": -5.79975,
        "feature_class": "P",
        "feature_code": "PPLA",
        "country_code": "MA",
        "admin1_code": 1,
        "admin2_code": 511,
        "admin3_code": 1651101071,
        "population": 688356,
        "dem": 20,
        "timezone": "Africa/Casablanca",
        "modification_date": "2016-11-02",
        "createdAt": "2020-12-15T12:45:37.997Z",
        "updatedAt": "2020-12-15T12:45:37.997Z"
      },
      {
        "objectId": "m7D3Pzlb0s",
        "geonameid": 2530155,
        "name": "Taounate",
        "asciiname": "Taounate",
        "alternatenames": "Taounat,Taounate,Taunat,Tawnat,Таунат",
        "latitude": 34.53661,
        "longitude": -4.64009,
        "feature_class": "P",
        "feature_code": "PPLA3",
        "country_code": "MA",
        "admin1_code": 3,
        "admin2_code": 531,
        "admin3_code": 1553101051,
        "population": 32802,
        "dem": 600,
        "timezone": "Africa/Casablanca",
        "modification_date": "2016-11-02",
        "createdAt": "2020-12-15T12:45:37.997Z",
        "updatedAt": "2020-12-15T12:45:37.997Z"
      },
      {
        "objectId": "QHdY1AlWxg",
        "geonameid": 2530048,
        "name": "Taourirt",
        "asciiname": "Taourirt",
        "latitude": 34.40731,
        "longitude": -2.89732,
        "feature_class": "P",
        "feature_code": "PPLA3",
        "country_code": "MA",
        "admin1_code": 2,
        "admin2_code": 533,
        "admin3_code": 853301331,
        "population": 82518,
        "dem": 394,
        "timezone": "Africa/Casablanca",
        "modification_date": "2016-11-04",
        "createdAt": "2020-12-15T12:45:37.997Z",
        "updatedAt": "2020-12-15T12:45:37.997Z"
      },
      {
        "objectId": "lXFKtvoGKV",
        "geonameid": 2529923,
        "name": "Tarfaya",
        "asciiname": "Tarfaya",
        "alternatenames": "Cabo Juby,Cabo Yubi,Cap Juby,Talfaia,Tarfaia,Tarfaja,Tarfaya,Villa Bens,tarufaya,trfayh,trfayt,Тарфая,طرفاية,طرفایه,タルファヤ",
        "latitude": 27.9392,
        "longitude": -12.92604,
        "feature_class": "P",
        "feature_code": "PPL",
        "country_code": "MA",
        "admin1_code": 11,
        "admin2_code": 537,
        "population": 5615,
        "dem": 5,
        "timezone": "Africa/Casablanca",
        "modification_date": "2018-02-16",
        "createdAt": "2020-12-15T12:45:37.997Z",
        "updatedAt": "2020-12-15T12:45:37.997Z"
      },
      {
        "objectId": "qwfZ5EO9Rz",
        "geonameid": 2529872,
        "name": "Targuist",
        "asciiname": "Targuist",
        "alternatenames": "Targvist,Таргвист",
        "latitude": 34.93769,
        "longitude": -4.31856,
        "feature_class": "P",
        "feature_code": "PPLA3",
        "country_code": "MA",
        "admin1_code": 1,
        "admin2_code": 51,
        "admin3_code": 1505101071,
        "population": 11560,
        "dem": 1029,
        "timezone": "Africa/Casablanca",
        "modification_date": "2018-05-21",
        "createdAt": "2020-12-15T12:45:37.997Z",
        "updatedAt": "2020-12-15T12:45:37.997Z"
      },
      {
        "objectId": "dkQuC7ifFV",
        "geonameid": 2529649,
        "name": "Taroudant",
        "asciiname": "Taroudant",
        "alternatenames": "Taroudannt,Taroudant,Tarudant,Tarudantas,Tarudante,ta lu dan te,tarwdant,Тарудант,تارودانت,塔魯丹特",
        "latitude": 30.47028,
        "longitude": -8.87695,
        "feature_class": "P",
        "feature_code": "PPLA3",
        "country_code": "MA",
        "admin1_code": 9,
        "admin2_code": 541,
        "admin3_code": 454101131,
        "population": 71133,
        "dem": 237,
        "timezone": "Africa/Casablanca",
        "modification_date": "2016-11-02",
        "createdAt": "2020-12-15T12:45:37.996Z",
        "updatedAt": "2020-12-15T12:45:37.996Z"
      },
      {
        "objectId": "9KTF0rJo4R",
        "geonameid": 11396026,
        "name": "Tayroukt",
        "asciiname": "Tayroukt",
        "latitude": 35.04142,
        "longitude": -5.23434,
        "feature_class": "P",
        "feature_code": "PPL",
        "country_code": "MA",
        "population": 200,
        "elevation": 1200,
        "dem": 947,
        "timezone": "Africa/Casablanca",
        "modification_date": "2016-12-24",
        "createdAt": "2020-12-15T12:45:39.525Z",
        "updatedAt": "2020-12-15T12:45:39.525Z"
      },
      {
        "objectId": "cAnjYHkFcl",
        "geonameid": 2529317,
        "name": "Taza",
        "asciiname": "Taza",
        "alternatenames": "Taza,ta zha,tazh,tazt,Таза,Таза қаласы,תאזה,تازة,تازه,تازہ,塔扎",
        "latitude": 34.21,
        "longitude": -4.01,
        "feature_class": "P",
        "feature_code": "PPLA2",
        "country_code": "MA",
        "admin1_code": 3,
        "admin2_code": 561,
        "admin3_code": 1556101111,
        "population": 141890,
        "dem": 530,
        "timezone": "Africa/Casablanca",
        "modification_date": "2016-11-02",
        "createdAt": "2020-12-15T12:45:37.996Z",
        "updatedAt": "2020-12-15T12:45:37.996Z"
      },
      {
        "objectId": "OHbrffgvZw",
        "geonameid": 2529013,
        "name": "Temara",
        "asciiname": "Temara",
        "alternatenames": "Kasba Temara,Temara",
        "latitude": 33.92866,
        "longitude": -6.90656,
        "feature_class": "P",
        "feature_code": "PPLA3",
        "country_code": "MA",
        "admin1_code": 4,
        "admin2_code": 501,
        "admin3_code": 1050101071,
        "population": 313510,
        "dem": 73,
        "timezone": "Africa/Casablanca",
        "modification_date": "2017-12-06",
        "createdAt": "2020-12-15T12:45:37.996Z",
        "updatedAt": "2020-12-15T12:45:37.996Z"
      },
      {
        "objectId": "hvbVlTGKzl",
        "geonameid": 2528910,
        "name": "Tétouan",
        "asciiname": "Tetouan",
        "alternatenames": "TTU,Tehtuan,Tetouan,Tetouán,Tetuan,Tetuanas,Tetuano,Tetuao,Tetuán,Tetuão,Tétouan,de tu an,teto'una,teto~uan,tetuan,ttwan,Τετουάν,Тетуан,Тетуан қаласы,Тэтуан,תטואן,تطوان,तेतोउन,თეტუანი,テトゥアン,得土安,테투안",
        "latitude": 35.57845,
        "longitude": -5.36837,
        "feature_class": "P",
        "feature_code": "PPLA2",
        "country_code": "MA",
        "admin1_code": 1,
        "admin2_code": 571,
        "population": 326261,
        "dem": 121,
        "timezone": "Africa/Casablanca",
        "modification_date": "2019-09-05",
        "createdAt": "2020-12-15T12:45:37.996Z",
        "updatedAt": "2020-12-15T12:45:37.996Z"
      },
      {
        "objectId": "zlvokwnsPS",
        "geonameid": 2528659,
        "name": "Tiflet",
        "asciiname": "Tiflet",
        "latitude": 33.89469,
        "longitude": -6.30649,
        "feature_class": "P",
        "feature_code": "PPLA3",
        "country_code": "MA",
        "admin1_code": 4,
        "admin2_code": 291,
        "admin3_code": 1029101051,
        "population": 70010,
        "dem": 340,
        "timezone": "Africa/Casablanca",
        "modification_date": "2016-11-02",
        "createdAt": "2020-12-15T12:45:37.996Z",
        "updatedAt": "2020-12-15T12:45:37.996Z"
      },
      {
        "objectId": "1K9qsKMJvM",
        "geonameid": 2527915,
        "name": "Tinghir",
        "asciiname": "Tinghir",
        "alternatenames": "Tineghir,Tinerhir,Tinghir,Tinrhir",
        "latitude": 31.51472,
        "longitude": -5.53278,
        "feature_class": "P",
        "feature_code": "PPLA2",
        "country_code": "MA",
        "admin1_code": 8,
        "admin2_code": 577,
        "population": 36795,
        "dem": 1281,
        "timezone": "Africa/Casablanca",
        "modification_date": "2016-11-29",
        "createdAt": "2020-12-15T12:45:37.996Z",
        "updatedAt": "2020-12-15T12:45:37.996Z"
      },
      {
        "objectId": "X4g1sE7NgR",
        "geonameid": 2527645,
        "name": "Tirhanimîne",
        "asciiname": "Tirhanimine",
        "latitude": 35.23619,
        "longitude": -3.95453,
        "feature_class": "P",
        "feature_code": "PPL",
        "country_code": "MA",
        "admin1_code": 1,
        "admin2_code": 51,
        "population": 55827,
        "dem": 209,
        "timezone": "Africa/Casablanca",
        "modification_date": "2016-11-29",
        "createdAt": "2020-12-15T12:45:37.996Z",
        "updatedAt": "2020-12-15T12:45:37.996Z"
      },
      {
        "objectId": "z9gMajH7tv",
        "geonameid": 2527089,
        "name": "Tiznit",
        "asciiname": "Tiznit",
        "alternatenames": "Tiznit,Tiznitas,ti zi ni te,tznyt,Тизнит,تزنيت,تزنیت,提茲尼特",
        "latitude": 29.69742,
        "longitude": -9.73162,
        "feature_class": "P",
        "feature_code": "PPLA3",
        "country_code": "MA",
        "admin1_code": 9,
        "admin2_code": 581,
        "admin3_code": 458101071,
        "population": 55092,
        "dem": 240,
        "timezone": "Africa/Casablanca",
        "modification_date": "2016-11-02",
        "createdAt": "2020-12-15T12:45:37.996Z",
        "updatedAt": "2020-12-15T12:45:37.996Z"
      },
      {
        "objectId": "XNv1Fc41K0",
        "geonameid": 2526981,
        "name": "Tmourghout",
        "asciiname": "Tmourghout",
        "alternatenames": "Tamoughout,Tamourhout,Tamrghoute,Tmourghout,Tmourhout",
        "latitude": 33.9065,
        "longitude": -4.02696,
        "feature_class": "P",
        "feature_code": "PPL",
        "country_code": "MA",
        "admin1_code": 3,
        "admin2_code": 561,
        "admin3_code": 1556109052,
        "population": 1250,
        "elevation": 900,
        "dem": 899,
        "timezone": "Africa/Casablanca",
        "modification_date": "2016-11-02",
        "createdAt": "2020-12-15T12:45:37.996Z",
        "updatedAt": "2020-12-15T12:45:37.996Z"
      },
      {
        "objectId": "Lm2bOFt2X7",
        "geonameid": 11524357,
        "name": "Torord - طرورد",
        "asciiname": "Torord - trwrd",
        "latitude": 31.16767,
        "longitude": -8.05767,
        "feature_class": "P",
        "feature_code": "PPLL",
        "country_code": "MA",
        "population": 426,
        "dem": 1019,
        "timezone": "Africa/Casablanca",
        "modification_date": "2017-05-01",
        "createdAt": "2020-12-15T12:45:39.525Z",
        "updatedAt": "2020-12-15T12:45:39.525Z"
      },
      {
        "objectId": "pkxS2pa8mM",
        "geonameid": 2526488,
        "name": "Youssoufia",
        "asciiname": "Youssoufia",
        "alternatenames": "Louis Gentil,Youssoufia",
        "latitude": 32.24634,
        "longitude": -8.52941,
        "feature_class": "P",
        "feature_code": "PPLA3",
        "country_code": "MA",
        "admin1_code": 7,
        "admin2_code": 431,
        "admin3_code": 1143101131,
        "population": 64910,
        "dem": 302,
        "timezone": "Africa/Casablanca",
        "modification_date": "2016-11-02",
        "createdAt": "2020-12-15T12:45:37.996Z",
        "updatedAt": "2020-12-15T12:45:37.996Z"
      },
      {
        "objectId": "6gUKT6ONkV",
        "geonameid": 2526459,
        "name": "Zag",
        "asciiname": "Zag",
        "alternatenames": "Zag",
        "latitude": 28.0221,
        "longitude": -9.29397,
        "feature_class": "P",
        "feature_code": "PPL",
        "country_code": "MA",
        "admin1_code": 10,
        "admin2_code": 71,
        "admin3_code": 307101031,
        "population": 7751,
        "dem": 410,
        "timezone": "Africa/Casablanca",
        "modification_date": "2019-10-01",
        "createdAt": "2020-12-15T12:45:37.996Z",
        "updatedAt": "2020-12-15T12:45:37.996Z"
      },
      {
        "objectId": "Pv0jbKtD2F",
        "geonameid": 2526452,
        "name": "Zagora",
        "asciiname": "Zagora",
        "alternatenames": "OZG,Zagora,Загора",
        "latitude": 30.33241,
        "longitude": -5.8384,
        "feature_class": "P",
        "feature_code": "PPLA3",
        "country_code": "MA",
        "admin1_code": 8,
        "admin2_code": 587,
        "admin3_code": 458701131,
        "population": 35154,
        "dem": 733,
        "timezone": "Africa/Casablanca",
        "modification_date": "2016-11-02",
        "createdAt": "2020-12-15T12:45:37.996Z",
        "updatedAt": "2020-12-15T12:45:37.996Z"
      },
      {
        "objectId": "nORsnFYEwv",
        "geonameid": 2526435,
        "name": "Zaïo",
        "asciiname": "Zaio",
        "alternatenames": "Toumiat Zaio,Toumiat Zaïo,Tumiat,Tumiat Zaio,Zaio,Zaïo",
        "latitude": 34.94282,
        "longitude": -2.7329,
        "feature_class": "P",
        "feature_code": "PPLA3",
        "country_code": "MA",
        "admin1_code": 2,
        "admin2_code": 381,
        "admin3_code": 838101071,
        "population": 30008,
        "dem": 198,
        "timezone": "Africa/Casablanca",
        "modification_date": "2016-11-29",
        "createdAt": "2020-12-15T12:45:37.996Z",
        "updatedAt": "2020-12-15T12:45:37.996Z"
      },
      {
        "objectId": "tcQ5028Mo5",
        "geonameid": 2541210,
        "name": "Zawyat an Nwaçer",
        "asciiname": "Zawyat an Nwacer",
        "alternatenames": "Nouaceur,Nouaseur,Nwacer,Nwaçer,Zawyat an Nwacer,Zawyat an Nwaçer",
        "latitude": 33.37981,
        "longitude": -7.61932,
        "feature_class": "P",
        "feature_code": "PPL",
        "country_code": "MA",
        "admin1_code": 6,
        "population": 12696,
        "dem": 195,
        "timezone": "Africa/Casablanca",
        "modification_date": "2020-06-11",
        "createdAt": "2020-12-15T12:45:37.997Z",
        "updatedAt": "2020-12-15T12:45:37.997Z"
      },
      {
        "objectId": "2kTFeSxyX2",
        "geonameid": 2526359,
        "name": "Zawyat ech Cheïkh",
        "asciiname": "Zawyat ech Cheikh",
        "alternatenames": "Zaouia ech Cheikh,Zaouia ech Cheïkh,Zavijja ash Shejkh,Zawyat ech Cheikh,Zawyat ech Cheïkh,Zouiat ech Cheikh,Zouiat ech Cheïkh,Завийя аш Шейх",
        "latitude": 32.64445,
        "longitude": -5.91826,
        "feature_class": "P",
        "feature_code": "PPL",
        "country_code": "MA",
        "admin1_code": 5,
        "population": 2000,
        "dem": 718,
        "timezone": "Africa/Casablanca",
        "modification_date": "2017-08-02",
        "createdAt": "2020-12-15T12:45:37.996Z",
        "updatedAt": "2020-12-15T12:45:37.996Z"
      }
    ]
  }